warouter.py
warouter-0.1.1.dist-info/RECORD
warouter-0.1.1.dist-info/metadata.json
warouter-0.1.1.dist-info/DESCRIPTION.rst
warouter-0.1.1.dist-info/zip-safe
warouter-0.1.1.dist-info/METADATA
warouter-0.1.1.dist-info/top_level.txt
warouter-0.1.1.dist-info/WHEEL
