Metadata-Version: 2.0
Name: warouter
Version: 0.1.1
Summary: Warouter is a simple routing wrapper around webapp2.
Home-page: https://github.com/remcohaszing/python-warouter
Author: Remco Haszing
Author-email: remcohaszing@gmail.com
License: MIT
Platform: UNKNOWN
Requires-Dist: webapp2
Requires-Dist: webob
Provides-Extra: docs
Requires-Dist: sphinx; extra == 'docs'
Requires-Dist: sphinxcontrib-napoleon; extra == 'docs'
